{
    "topAdminPrivateKey": "d7410fb6e0c10ce73cc3179f73e7bb6adabbe8fb17570a47eb8195e17ed0c3f4",
    "flow": [
        {
            "type": "CREATE_ACCOUNT",
            "data": {
                "firstName": "John",
                "surname": "Doe",
                "organization": "UserAdmin Organization",
                "street": "Main Street",
                "number": "1",
                "zip": "01234",
                "city": "Anytown",
                "country": "USA",
                "state": "Anystate",
                "address": "0x71c31ff1faa17b1cb5189fd845e0cca650d215d3",
                "privateKey": "0xbfb423a193614c6712efd02951289192c20d70b3fc8a8b7cdee73603fcead486",
                "rights": 1
            }
        },
        {
            "type": "CREATE_ACCOUNT",
            "data": {
                "firstName": "John",
                "surname": "Doe Two",
                "organization": "AssetAdmin Organization",
                "street": "Main Street",
                "number": "2",
                "zip": "01234",
                "city": "Anytown",
                "country": "USA",
                "state": "Anystate",
                "address": "0xcea1c413a570654fa85e78f7c17b755563fec5a5",
                "privateKey": "0x5c0b28bff67916a879953c50b25c73827ae0b777a2ad13abba2e4b67f843294e",
                "rights": 2
            }
        },
        {
            "type": "CREATE_ACCOUNT",
            "data": {
                "firstName": "John",
                "surname": "Doe Three",
                "organization": "AgreementAdmin Organization",
                "street": "Main Street",
                "number": "3",
                "zip": "01234",
                "city": "Anytown",
                "country": "USA",
                "state": "Anystate",
                "address": "0x583b3e16a27f3db4bdc4c1a5452eeed14619c8da",
                "privateKey": "0x37b3b1d577f61fac7afc161a12669361a7f308ad42c7b093dc10ff1781bb618d",
                "rights": 4
            }
        },
        {
            "type": "CREATE_ACCOUNT",
            "data": {
                "firstName": "John",
                "surname": "Doe Four",
                "organization": "AssetManager Organization",
                "street": "Main Street",
                "number": "4",
                "zip": "01234",
                "city": "Anytown",
                "country": "USA",
                "state": "Anystate",
                "address": "0x33496f621350cea01b18ea5b5c43c6c233c3f72d",
                "privateKey": "0x96ce644659ea5572aedc29296c866a62c36c6cdcafc8801c1c46d02abc8c0047",
                "rights": 24
            }
        },
        {
            "type": "CREATE_ACCOUNT",
            "data": {
                "firstName": "John",
                "surname": "Doe Five",
                "organization": "AssetManager Second Organization",
                "street": "Main Street",
                "number": "5",
                "zip": "01234",
                "city": "Anytown",
                "country": "USA",
                "state": "Anystate",
                "address": "0x51ba6877a2c4580d50f7ceece02e2f24e78ef123",
                "privateKey": "0x6ee02c057cda3019132c670b425e6caea4f055ac8f64377d2463f123e71babec",
                "rights": 24
            }
        },
        {
            "type": "CREATE_ACCOUNT",
            "data": {
                "firstName": "John",
                "surname": "Doe Six",
                "organization": "Trader Organization",
                "street": "Main Street",
                "number": "6",
                "zip": "01234",
                "city": "Anytown",
                "country": "USA",
                "state": "Anystate",
                "address": "0x4095f1db44884764C17c7A9A31B4Bf20f5779691",
                "privateKey": "0x9d66d342a3b6014a7cff6ff0379b192dbe193e43bb6979625c600c4996bb3b85",
                "rights": 16
            }
        },
        {
            "type": "CREATE_ACCOUNT",
            "data": {
                "firstName": "John",
                "surname": "Doe Seven",
                "organization": "Matcher Organization",
                "street": "Main Street",
                "number": "7",
                "zip": "01234",
                "city": "Anytown",
                "country": "USA",
                "state": "Anystate",
                "address": "0x585cc5c7829b1fd303ef5c019ed23815a205a59e",
                "privateKey": "0xe9a63e116f72c2e368376eb88c22fecf2a5e94a93464ff8802cf97caac657548",
                "rights": 63
            }
        },
        {
            "type": "CREATE_PRODUCING_ASSET",
            "data": {
                "smartMeter": "0x343854a430653571b4de6bf2b8c475f828036c30",
                "smartMeterPK": "12c5c7473dbdb92a524a93baa14ded529fe29acef8d269a3901c14a15e2b0f98",
                "owner": "0x33496f621350cea01b18ea5b5c43c6c233c3f72d",
                "matcher": "0x585cc5c7829b1fd303ef5c019ed23815a205a59e",
                "operationalSince": 1514764800,
                "capacityWh": 10000,
                "lastSmartMeterReadWh": 0,
                "active": true,
                "lastSmartMeterReadFileHash": "",
                "country": "USA",
                "region": "AnyState",
                "zip": "01234",
                "city": "Anytown",
                "street": "Main Street",
                "houseNumber": "8",
                "gpsLatitude": "0",
                "gpsLongitude": "0",
                "assetType": "Wind",
                "certificatesCreatedForWh": 0,
                "lastSmartMeterCO2OffsetRead": 0,
                "complianceRegistry": "none",
                "otherGreenAttributes": "N.A.",
                "typeOfPublicSupport": "N.A",
                "maxOwnerChanges": 3
            }
        },
        {
            "type": "CREATE_PRODUCING_ASSET",
            "data": {
                "smartMeter": "0x84a2c086ffa013d06285cdd303556ec9be5a1ff7",
                "smartMeterPK": "a05ddf7fe8302d117b516c0e401468a30c39a3e467ad3720381cf89500f0854b",
                "owner": "0x51ba6877a2c4580d50f7ceece02e2f24e78ef123",
                "matcher": "0x585cc5c7829b1fd303ef5c019ed23815a205a59e",
                "operationalSince": 1483228800,
                "capacityWh": 10,
                "lastSmartMeterReadWh": 0,
                "active": true,
                "lastSmartMeterReadFileHash": "",
                "country": "USA",
                "region": "AnyState",
                "zip": "01234",
                "city": "Anytown",
                "street": "Main Street",
                "houseNumber": "9",
                "gpsLatitude": "0",
                "gpsLongitude": "0",
                "assetType": "Solar",
                "certificatesCreatedForWh": 0,
                "lastSmartMeterCO2OffsetRead": 0,
                "complianceRegistry": "IREC",
                "otherGreenAttributes": "N.A.",
                "typeOfPublicSupport": "N.A",
                "maxOwnerChanges": 3
            }
        },
        {
            "type": "CREATE_PRODUCING_ASSET",
            "data": {
                "smartMeter": "0x00f4af465162c05843ea38d203d37f7aad2e2c17",
                "smartMeterPK": "09f08bc14bfdaf427fdd0eb676db21a86fa908a25870158345e4f847b5ada35e",
                "owner": "0x33496f621350cea01b18ea5b5c43c6c233c3f72d",
                "matcher": "0x585cc5c7829b1fd303ef5c019ed23815a205a59e",
                "operationalSince": 1514764800,
                "capacityWh": 10000,
                "lastSmartMeterReadWh": 0,
                "active": true,
                "lastSmartMeterReadFileHash": "",
                "country": "USA",
                "region": "AnyState",
                "zip": "01234",
                "city": "Anytown",
                "street": "Main Street",
                "houseNumber": "10",
                "gpsLatitude": "0",
                "gpsLongitude": "0",
                "assetType": "BiomassGas",
                "certificatesCreatedForWh": 0,
                "lastSmartMeterCO2OffsetRead": 0,
                "complianceRegistry": "TIGR",
                "otherGreenAttributes": "N.A.",
                "typeOfPublicSupport": "N.A",
                "maxOwnerChanges": 3
            }
        },
        {
            "type": "CREATE_CONSUMING_ASSET",
            "data": {
                "smartMeter": "0x1112ec367b20d2bffd40ee11523c3d36d61adf1b",
                "smartMeterPK": "50764e302e4ed8ce624003deca642c03ce06934fe77585175c5576723f084d4c",
                "owner": "0x33496f621350cea01b18ea5b5c43c6c233c3f72d",
                "matcher": "0x585cc5c7829b1fd303ef5c019ed23815a205a59e",
                "operationalSince": 1529971200,
                "capacityWh": 5000,
                "lastSmartMeterReadWh": 0,
                "active": true,
                "lastSmartMeterReadFileHash": "",
                "country": "USA",
                "region": "AnyState",
                "zip": "01234",
                "city": "Anytown",
                "street": "Main Street",
                "houseNumber": "11",
                "gpsLatitude": "0",
                "gpsLongitude": "0",
                "maxCapacitySet": true,
                "certificatesUsedForWh": 0
            }
        },
        {
            "type": "SLEEP",
            "data": 2000
        },
        {
            "type": "INITIALIZE_CERTIFICATES",
            "data": {
                "assetId": 0,
                "assetOwner": "0x33496f621350cea01b18ea5b5c43c6c233c3f72d",
                "assetOwnerPK": "0x96ce644659ea5572aedc29296c866a62c36c6cdcafc8801c1c46d02abc8c0047"
            }
        },
        {
            "type": "INITIALIZE_CERTIFICATES",
            "data": {
                "assetId": 1,
                "assetOwner": "0x51ba6877a2c4580d50f7ceece02e2f24e78ef123",
                "assetOwnerPK": "0x6ee02c057cda3019132c670b425e6caea4f055ac8f64377d2463f123e71babec"
            }
        },
        {
            "type": "INITIALIZE_CERTIFICATES",
            "data": {
                "assetId": 2,
                "assetOwner": "0x33496f621350cea01b18ea5b5c43c6c233c3f72d",
                "assetOwnerPK": "0x96ce644659ea5572aedc29296c866a62c36c6cdcafc8801c1c46d02abc8c0047"
            }
        },
        {
            "type": "SAVE_SMARTMETER_READ_PRODUCING",
            "data": {
                "assetId": 0,
                "meterreading": 10,
                "smartMeter": "0x343854a430653571b4de6bf2b8c475f828036c30",
                "smartMeterPK": "0x12c5c7473dbdb92a524a93baa14ded529fe29acef8d269a3901c14a15e2b0f98",
                "filehash": "newMeterRead"
            }
        },
        {
            "type": "SAVE_SMARTMETER_READ_CONSUMING",
            "data": {
                "assetId": 0,
                "meterreading": 10,
                "smartMeter": "0x1112ec367b20d2bffd40ee11523c3d36d61adf1b",
                "smartMeterPK": "0x50764e302e4ed8ce624003deca642c03ce06934fe77585175c5576723f084d4c",
                "filehash": "newMeterRead"
            }
        },
        {
            "type": "TRANSFER_CERTIFICATE",
            "data": {
                "certId": 0,
                "assetOwner": "0x33496f621350cea01b18ea5b5c43c6c233c3f72d",
                "assetOwnerPK": "0x96ce644659ea5572aedc29296c866a62c36c6cdcafc8801c1c46d02abc8c0047",
                "addressTo": "0x4095f1db44884764C17c7A9A31B4Bf20f5779691"
            }
        },
        {
            "type": "SAVE_SMARTMETER_READ_PRODUCING",
            "data": {
                "assetId": 0,
                "meterreading": 15,
                "smartMeter": "0x343854a430653571b4de6bf2b8c475f828036c30",
                "smartMeterPK": "0x12c5c7473dbdb92a524a93baa14ded529fe29acef8d269a3901c14a15e2b0f98",
                "filehash": "newMeterRead"
            }
        },
        {
            "type": "SPLIT_CERTIFICATE",
            "data": {
                "certId":1,
                "assetOwner": "0x33496f621350cea01b18ea5b5c43c6c233c3f72d",
                "assetOwnerPK": "0x96ce644659ea5572aedc29296c866a62c36c6cdcafc8801c1c46d02abc8c0047",
                "splitValue": 3
            }
        },
        {
            "type": "SAVE_SMARTMETER_READ_PRODUCING",
            "data": {
                "assetId": 0,
                "meterreading": 20,
                "smartMeter": "0x343854a430653571b4de6bf2b8c475f828036c30",
                "smartMeterPK": "0x12c5c7473dbdb92a524a93baa14ded529fe29acef8d269a3901c14a15e2b0f98",
                "filehash": "newMeterRead"
            }
        },
        {
            "type": "SET_ERC20_CERTIFICATE",
            "data": {
                "certId":4,
                "assetOwner": "0x33496f621350cea01b18ea5b5c43c6c233c3f72d",
                "assetOwnerPK": "0x96ce644659ea5572aedc29296c866a62c36c6cdcafc8801c1c46d02abc8c0047",
                "price": 1000,
                "testAccount": "0x4095f1db44884764C17c7A9A31B4Bf20f5779691"
            }
        },
        {
            "type": "BUY_CERTIFICATE",
            "data": {
                "certId": 4,
                "price": 1000,
                "buyer": "0x4095f1db44884764C17c7A9A31B4Bf20f5779691",
                "buyerPK": "0x9d66d342a3b6014a7cff6ff0379b192dbe193e43bb6979625c600c4996bb3b85",
                "assetOwner": "0x33496f621350cea01b18ea5b5c43c6c233c3f72d"
            }
        },
        {
            "type": "SAVE_SMARTMETER_READ_PRODUCING",
            "data": {
                "assetId": 1,
                "meterreading": 5,
                "smartMeter": "0x84a2c086ffa013d06285cdd303556ec9be5a1ff7",
                "smartMeterPK": "0xa05ddf7fe8302d117b516c0e401468a30c39a3e467ad3720381cf89500f0854b",
                "filehash": "newMeterRead"
            }
        },
        {
            "type": "CREATE_DEMAND",
            "data": {
                "trader": "0x4095f1db44884764C17c7A9A31B4Bf20f5779691",
                "traderPK": "0x9d66d342a3b6014a7cff6ff0379b192dbe193e43bb6979625c600c4996bb3b85",
                "timeframe": "hourly",
                "pricePerCertifiedWh": 10,
                "currency": "Ether",
                "producingAsset": 0,
                "consumingAsset": 0,
                "country": "string",
                "region": "string",
                "assettype": "BiomassGas",
                "minCO2Offset": 10,
                "otherGreenAttributes": "string",
                "typeOfPublicSupport": "string",
                "targetWhPerPeriod": 10,
                "registryCompliance": "EEC"
            }
        },
        {
            "type": "CREATE_SUPPLY",
            "data": {
                "assetId": 1,
                "assetOwner": "0x51ba6877a2c4580d50f7ceece02e2f24e78ef123",
                "assetOwnerPK": "0x6ee02c057cda3019132c670b425e6caea4f055ac8f64377d2463f123e71babec",
                "price": 10,
                "currency": "USD",
                "availableWh": 10,
                "timeframe": "hourly"
            }
        },
        {
            "type": "MAKE_AGREEMENT",
            "data": {
              "creator": "0x4095f1db44884764C17c7A9A31B4Bf20f5779691",
              "creatorPK": "0x9d66d342a3b6014a7cff6ff0379b192dbe193e43bb6979625c600c4996bb3b85",
              "startTime": -1,
              "endTime": 3600,
              "price": 10,
              "currency": "USD",
              "timeframe": "hourly",
              "period": 10,
              "currentWh": 0,
              "currentPeriod": 0,
              "demandId": 0,
              "supplyId": 0,
              "allowedMatcher": "0x585cc5c7829b1fd303ef5c019ed23815a205a59e"
            }
        },
        {
            "type": "APPROVE_AGREEMENT",
            "data": {
                "agreementId": 0,
                "agree": "0x51ba6877a2c4580d50f7ceece02e2f24e78ef123",
                "agreePK": "0x6ee02c057cda3019132c670b425e6caea4f055ac8f64377d2463f123e71babec"
            }
        },
        {
            "type": "SAVE_SMARTMETER_READ_PRODUCING",
            "data": {
                "assetId": 1,
                "meterreading": 200,
                "smartMeter": "0x84a2c086ffa013d06285cdd303556ec9be5a1ff7",
                "smartMeterPK": "0xa05ddf7fe8302d117b516c0e401468a30c39a3e467ad3720381cf89500f0854b",
                "filehash": "newMeterRead"
            }
        }
    ]
}
